<?xml version='1.0' encoding='utf-8'?>
<annotation><folder>DATASET</folder><filename>129.jpg</filename><size><width>512</width><height>512</height></size><object><name>west</name><bndbox><xmin>2</xmin><ymin>347</ymin><xmax>69</xmax><ymax>438</ymax></bndbox><pose>Unspecified</pose><truncated>0</truncated><difficult>0</difficult></object><object><name>8m</name><bndbox><xmin>69</xmin><ymin>347</ymin><xmax>136</xmax><ymax>438</ymax></bndbox><pose>Unspecified</pose><truncated>0</truncated><difficult>0</difficult></object><object><name>3s</name><bndbox><xmin>136</xmin><ymin>347</ymin><xmax>203</xmax><ymax>438</ymax></bndbox><pose>Unspecified</pose><truncated>0</truncated><difficult>0</difficult></object><object><name>west</name><bndbox><xmin>203</xmin><ymin>347</ymin><xmax>270</xmax><ymax>438</ymax></bndbox><pose>Unspecified</pose><truncated>0</truncated><difficult>0</difficult></object><object><name>4m</name><bndbox><xmin>270</xmin><ymin>347</ymin><xmax>337</xmax><ymax>438</ymax></bndbox><pose>Unspecified</pose><truncated>0</truncated><difficult>0</difficult></object><object><name>1m</name><bndbox><xmin>337</xmin><ymin>347</ymin><xmax>404</xmax><ymax>438</ymax></bndbox><pose>Unspecified</pose><truncated>0</truncated><difficult>0</difficult></object><object><name>7s</name><bndbox><xmin>404</xmin><ymin>347</ymin><xmax>471</xmax><ymax>438</ymax></bndbox><pose>Unspecified</pose><truncated>0</truncated><difficult>0</difficult></object></annotation>