<?xml version='1.0' encoding='utf-8'?>
<annotation><folder>DATASET</folder><filename>141.jpg</filename><size><width>512</width><height>512</height></size><object><name>9p</name><bndbox><xmin>11</xmin><ymin>40</ymin><xmax>81</xmax><ymax>136</ymax></bndbox><pose>Unspecified</pose><truncated>0</truncated><difficult>0</difficult></object><object><name>1m</name><bndbox><xmin>81</xmin><ymin>40</ymin><xmax>151</xmax><ymax>136</ymax></bndbox><pose>Unspecified</pose><truncated>0</truncated><difficult>0</difficult></object><object><name>1p</name><bndbox><xmin>151</xmin><ymin>40</ymin><xmax>221</xmax><ymax>136</ymax></bndbox><pose>Unspecified</pose><truncated>0</truncated><difficult>0</difficult></object><object><name>hatsu</name><bndbox><xmin>221</xmin><ymin>40</ymin><xmax>291</xmax><ymax>136</ymax></bndbox><pose>Unspecified</pose><truncated>0</truncated><difficult>0</difficult></object><object><name>3p</name><bndbox><xmin>291</xmin><ymin>40</ymin><xmax>361</xmax><ymax>136</ymax></bndbox><pose>Unspecified</pose><truncated>0</truncated><difficult>0</difficult></object><object><name>8m</name><bndbox><xmin>361</xmin><ymin>40</ymin><xmax>431</xmax><ymax>136</ymax></bndbox><pose>Unspecified</pose><truncated>0</truncated><difficult>0</difficult></object><object><name>5m</name><bndbox><xmin>431</xmin><ymin>40</ymin><xmax>501</xmax><ymax>136</ymax></bndbox><pose>Unspecified</pose><truncated>0</truncated><difficult>0</difficult></object></annotation>