<?xml version='1.0' encoding='utf-8'?>
<annotation><folder>DATASET</folder><filename>446.jpg</filename><size><width>512</width><height>512</height></size><object><name>4m</name><bndbox><xmin>25</xmin><ymin>289</ymin><xmax>93</xmax><ymax>381</ymax></bndbox><pose>Unspecified</pose><truncated>0</truncated><difficult>0</difficult></object><object><name>5p</name><bndbox><xmin>93</xmin><ymin>289</ymin><xmax>161</xmax><ymax>381</ymax></bndbox><pose>Unspecified</pose><truncated>0</truncated><difficult>0</difficult></object><object><name>5p</name><bndbox><xmin>161</xmin><ymin>289</ymin><xmax>229</xmax><ymax>381</ymax></bndbox><pose>Unspecified</pose><truncated>0</truncated><difficult>0</difficult></object><object><name>3m</name><bndbox><xmin>229</xmin><ymin>289</ymin><xmax>297</xmax><ymax>381</ymax></bndbox><pose>Unspecified</pose><truncated>0</truncated><difficult>0</difficult></object><object><name>5s</name><bndbox><xmin>297</xmin><ymin>289</ymin><xmax>365</xmax><ymax>381</ymax></bndbox><pose>Unspecified</pose><truncated>0</truncated><difficult>0</difficult></object><object><name>9p</name><bndbox><xmin>365</xmin><ymin>289</ymin><xmax>433</xmax><ymax>381</ymax></bndbox><pose>Unspecified</pose><truncated>0</truncated><difficult>0</difficult></object><object><name>3m</name><bndbox><xmin>433</xmin><ymin>289</ymin><xmax>501</xmax><ymax>381</ymax></bndbox><pose>Unspecified</pose><truncated>0</truncated><difficult>0</difficult></object></annotation>